face_recognition_ai/__init__.py
face_recognition_ai/face_recognition.py
face_recognition_ai-0.0.2.dist-info/METADATA
face_recognition_ai-0.0.2.dist-info/WHEEL
face_recognition_ai-0.0.2.dist-info/top_level.txt
face_recognition_ai-0.0.2.dist-info/RECORD
