Metadata-Version: 2.1
Name: face-recognition-ai
Version: 0.0.2
Summary: A face recognition system using yoloface and facenet
Home-page: https://github.com/muntakim1/face-recognition-ai
Author: Muntakimur Rahaman
Author-email: muntakim.cse@gmail.com
License: MIT
Classifier: License :: OSI Approved :: MIT License
Classifier: Programming Language :: Python :: 3.10
Classifier: Topic :: Scientific/Engineering :: Image Recognition
Classifier: Topic :: Scientific/Engineering :: Artificial Intelligence
Requires-Python: >=3.10
Requires-Dist: facenet-pytorch
Requires-Dist: PyYaml
Requires-Dist: joblib
Requires-Dist: opencv-python
Requires-Dist: yolo5face
